a2dl/__init__.py
a2dl/a2dl.py
a2dl/image.py
a2dl/data/codeUse.adoc
a2dl/data/exampleDiagram-compressed.drawio
a2dl/data/exampleDiagram.drawio
a2dl/data/exampleDiagramFromLibrary-compressed-old.drawio
a2dl/data/exampleDiagramFromLibrary-compressed-old.drawio.new.drawio
a2dl/data/exampleDiagramFromLibrary-old.drawio
a2dl/data/exampleDiagramFromLibrary-old.drawio.new.drawio
a2dl/data/exampleDocument.adoc
a2dl/data/exampleLibrary.xml
a2dl/data/imageOverview.adoc
a2dl/data/template_article.adoc
a2dl/data/test-generated-icon-from-exampleDocument.drawio
a2dl/data/test-generated-library-from-data-folder.xml
a2dl/data/test-generated-library-from-exampleDocument.xml
a2dl/data/test-generated-library.xml
a2dl/data/images/1.png
a2dl/data/images/10.png
a2dl/data/images/11.png
a2dl/data/images/12.png
a2dl/data/images/13.png
a2dl/data/images/14.png
a2dl/data/images/15.png
a2dl/data/images/16.png
a2dl/data/images/17.png
a2dl/data/images/18.png
a2dl/data/images/19.png
a2dl/data/images/2.png
a2dl/data/images/20.png
a2dl/data/images/21.png
a2dl/data/images/22.png
a2dl/data/images/23.png
a2dl/data/images/24.png
a2dl/data/images/25.png
a2dl/data/images/26.png
a2dl/data/images/27.png
a2dl/data/images/28.png
a2dl/data/images/29.png
a2dl/data/images/3.png
a2dl/data/images/30.png
a2dl/data/images/31.png
a2dl/data/images/32.png
a2dl/data/images/33.png
a2dl/data/images/34.png
a2dl/data/images/35.png
a2dl/data/images/36.png
a2dl/data/images/37.png
a2dl/data/images/38.png
a2dl/data/images/39.png
a2dl/data/images/4.png
a2dl/data/images/40.png
a2dl/data/images/41.png
a2dl/data/images/42.png
a2dl/data/images/43.png
a2dl/data/images/44.png
a2dl/data/images/45.png
a2dl/data/images/46.png
a2dl/data/images/47.png
a2dl/data/images/48.png
a2dl/data/images/49.png
a2dl/data/images/5.png
a2dl/data/images/50.png
a2dl/data/images/51.png
a2dl/data/images/53.png
a2dl/data/images/54.png
a2dl/data/images/56.png
a2dl/data/images/57.png
a2dl/data/images/58.png
a2dl/data/images/59.png
a2dl/data/images/6.png
a2dl-0.1.2.dist-info/LICENSE.txt
a2dl-0.1.2.dist-info/METADATA
a2dl-0.1.2.dist-info/WHEEL
a2dl-0.1.2.dist-info/entry_points.txt
a2dl-0.1.2.dist-info/top_level.txt
a2dl-0.1.2.dist-info/RECORD
