Metadata-Version: 2.1
Name: a2dl
Version: 0.1.2
Summary: Generate draw.io icon libraries from AsciiDoc-based descriptions.
Home-page: https://tigabeatz.net
Author: tigabeatz
Author-email: tigabeatz@cccwi.de
Classifier: Programming Language :: Python :: 3
Classifier: License :: OSI Approved :: MIT License
Classifier: Development Status :: 5 - Production/Stable
Requires-Python: >=3.10
License-File: LICENSE.txt
